LICENSE
MANIFEST.in
README.md
commands.md
gemini_install.py
heaper.py
make.sh
master-test.sh
requirements.txt
setup.py
t.py
t.sh
to-sample.py
docs/EXAMPLES.rst
docs/Makefile
docs/TODO.rst
docs/build.sh
docs/conf.py
docs/gemini.ai
docs/gemini.png
docs/index.rst
docs/requirements.txt
docs/_static/labibi.css
docs/_static/labibi.js
docs/content/acknowledgements.rst
docs/content/api.rst
docs/content/browser.rst
docs/content/caveats.rst
docs/content/database_schema.rst
docs/content/faq.rst
docs/content/functional_annotation.rst
docs/content/genotype_query_engines.rst
docs/content/history.rst
docs/content/installation.rst
docs/content/other.rst
docs/content/preprocessing.rst
docs/content/querying.rst
docs/content/quick_start.rst
docs/content/tools.rst
docs/images/browser-query.png
docs/images/gene_wise_example.png
docs/images/overview.png
docs/images/query-speed.png
docs/templates/layout.html
docs/templates/page.html
docs/templates/sidebar-intro.html
docs/themes/rtd/theme.conf
docs/themes/rtd/static/rtd.css_t
gemini/GeminiQuery.py
gemini/__init__.py
gemini/anno_info.py
gemini/annotations.py
gemini/compression.py
gemini/config.py
gemini/database.py
gemini/dgidb.py
gemini/gemini_actionable_mutations.py
gemini/gemini_amend.py
gemini/gemini_annotate.py
gemini/gemini_bcolz.py
gemini/gemini_browser.py
gemini/gemini_constants.py
gemini/gemini_dbinfo.py
gemini/gemini_dump.py
gemini/gemini_load.py
gemini/gemini_load_chunk.py
gemini/gemini_main.py
gemini/gemini_merge_chunks.py
gemini/gemini_plot.py
gemini/gemini_query.py
gemini/gemini_region.py
gemini/gemini_set_somatic.py
gemini/gemini_stats.py
gemini/gemini_subjects.py
gemini/gemini_update.py
gemini/gemini_utils.py
gemini/gemini_windower.py
gemini/gene_table.py
gemini/genewise.py
gemini/gim.py
gemini/infotag.py
gemini/install-data.py
gemini/mendelianerror.py
gemini/pdict.py
gemini/ped.py
gemini/popgen.py
gemini/sql_utils.py
gemini/stats.py
gemini/structural_variants.py
gemini/tool_burden_tests.py
gemini/tool_fusions.py
gemini.egg-info/PKG-INFO
gemini.egg-info/SOURCES.txt
gemini.egg-info/dependency_links.txt
gemini.egg-info/not-zip-safe
gemini.egg-info/requires.txt
gemini.egg-info/top_level.txt
